{"cameraMode":{"drawMode":0,"name":"Shaded","section":"Shading Mode"},"sceneLighting":false,"audioPlay":false,"sceneViewState":{"m_AlwaysRefresh":false,"showFog":true,"showSkybox":false,"showFlares":true,"showImageEffects":true,"showParticleSystems":true,"showVisualEffectGraphs":true,"m_FxEnabled":true},"in2DMode":false,"pivot":{"x":-10.982556343078614,"y":0.12157900631427765,"z":10.602855682373047},"rotation":{"x":-0.1255558729171753,"y":-0.4826005697250366,"z":0.07012821733951569,"w":-0.8639833331108093},"size":0.8660253882408142,"orthographic":false}